gacilator/__init__.py
gacilator/example.py
gacilator/gacilator.py
calculator_pkg_GACI_GIT-0.0.5.dist-info/LICENSE.md
calculator_pkg_GACI_GIT-0.0.5.dist-info/METADATA
calculator_pkg_GACI_GIT-0.0.5.dist-info/WHEEL
calculator_pkg_GACI_GIT-0.0.5.dist-info/top_level.txt
calculator_pkg_GACI_GIT-0.0.5.dist-info/RECORD
