Metadata-Version: 2.1
Name: calculator-pkg-GACI-GIT
Version: 0.0.5
Summary: A basic calculator package
Home-page: https://github.com/Gaci-git/calculator_package
Author: Gabriele C
Author-email: gabriele@example.com
License: UNKNOWN
Project-URL: Bug Tracker, https://github.com/pypa/sampleproject/issues
Platform: UNKNOWN
Classifier: Programming Language :: Python :: 3
Classifier: License :: OSI Approved :: MIT License
Classifier: Operating System :: OS Independent
Requires-Python: >=3.6
License-File: LICENSE.md
